LICENCE.txt
MANIFEST.in
README.md
README_PyPi.rst
setup.py
moviebarcode/__init__.py
moviebarcode/color_barcode_gen.py
moviebarcode/color_gen.py
moviebarcode/helpers.py
moviebarcode/image_barcode_gen.py
moviebarcode/k_means_colors.py
moviebarcode/movie_barcode.py
moviebarcode/pil_colors.py
moviebarcode/run_ffmpeg.py
moviebarcodecreator.egg-info/PKG-INFO
moviebarcodecreator.egg-info/SOURCES.txt
moviebarcodecreator.egg-info/dependency_links.txt
moviebarcodecreator.egg-info/entry_points.txt
moviebarcodecreator.egg-info/requires.txt
moviebarcodecreator.egg-info/top_level.txt